governance_common/alembic.ini
governance_common/chatbots.py
governance_common/migrations/README
governance_common/migrations/env.py
governance_common/migrations/script.py.mako
governance_common/migrations/versions/436f2cd0a9d4_initial_database.py
governance_common/models.py
governance_common-0.0.10.dist-info/METADATA
governance_common-0.0.10.dist-info/WHEEL
governance_common-0.0.10.dist-info/RECORD
