Metadata-Version: 2.1
Name: governance-common
Version: 0.0.10
Summary: Governance common classes, to enable reuse in multiple apps
Author: Sebastian Montero
Author-email: sebastian.montero@gmail.com
Requires-Python: >=3.8.1,<4.0
Classifier: Programming Language :: Python :: 3
Classifier: Programming Language :: Python :: 3.9
Classifier: Programming Language :: Python :: 3.10
Classifier: Programming Language :: Python :: 3.11
Requires-Dist: SQLAlchemy (>=1.4,<3)
Requires-Dist: alembic (>=1.11.1,<2.0.0)
Requires-Dist: langchain (>=0.0.199,<0.0.200)
Requires-Dist: python-dotenv (>=1.0.0,<2.0.0)
